<IMNotifyApplicationUpdateRq>
    <HeaderInfo RqUID="RqUID" RqTm="" SPName="" SystemId=""/>
    <Application>
        <ClientInfo>
            <LastName></LastName>
            <FirstName></FirstName>
            <MiddleName></MiddleName>
            <BirthDate></BirthDate>
            <DocNumber></DocNumber>
            <DocType></DocType>
            <ClientEPCId></ClientEPCId>
            <MobilePhone></MobilePhone>
            <Email></Email>
            <CustomerValue></CustomerValue>
        </ClientInfo>
        <ApplicationInfo>
            <IntegrationId></IntegrationId>
            <ModificationNum></ModificationNum>
            <OptyType></OptyType>
            <UKCode></UKCode>
            <Channel></Channel>
            <Currency></Currency>
            <Comments></Comments>
            <CreatedByLogin></CreatedByLogin>
            <CreatedByWorkPhone></CreatedByWorkPhone>
            <CreatedByEmail></CreatedByEmail>
            <LastAppLogin></LastAppLogin>
            <Status></Status>
            <CRMProductId></CRMProductId>
            <CRMLinkedOptyNumber></CRMLinkedOptyNumber>
            <Stage></Stage>
            <StatusChangeDate></StatusChangeDate>
            <OwnerLogin></OwnerLogin>
            <OwnerWorkPhone></OwnerWorkPhone>
            <OwnerEmail></OwnerEmail>
            <AppCreatorDivision></AppCreatorDivision>
            <RegistrationOffice></RegistrationOffice>
            <Organization></Organization>
            <RejectionReason></RejectionReason>
            <ContractPlanDate></ContractPlanDate>
            <CreditCategory></CreditCategory>
            <FeeFrequency></FeeFrequency>
            <Source></Source>
            <WaveId></WaveId>
            <UFSId></UFSId>
            <StatusDetails></StatusDetails>
            <CRMOptyNumber></CRMOptyNumber>
            <PreviousState></PreviousState>
            <CurrentState></CurrentState>
            <LastVisit></LastVisit>
            <LastUpdDt></LastUpdDt>
            <Sum></Sum>
            <PCT></PCT>
            <Period></Period>
            <EFF_PCT></EFF_PCT>
            <EFF_Sum></EFF_Sum>
            <FinalSum></FinalSum>
            <Limit></Limit>
            <Rate></Rate>
            <FirstService></FirstService>
            <SecondService></SecondService>
            <AdditionalCard></AdditionalCard>
            <AeroflotCode></AeroflotCode>
            <IncMobileBank></IncMobileBank>
            <IncAutoPay></IncAutoPay>
            <SPOOBKCode></SPOOBKCode>
            <CardTarifCode></CardTarifCode>
            <PeriodDay></PeriodDay>
            <GetPct></GetPct>
            <FirstPay></FirstPay>
            <MinimumBalance></MinimumBalance>
            <CapitalizationFlg></CapitalizationFlg>
            <MonthlyPayment></MonthlyPayment>
            <Price></Price>
            <IncludeInsurance></IncludeInsurance>
            <MotherFund></MotherFund>
            <MinimumBalancePCT></MinimumBalancePCT>
            <InsuranceSum></InsuranceSum>
            <PropertyInsurance></PropertyInsurance>
            <InsurancePeriod></InsurancePeriod>
            <AnotherPersonInsurance></AnotherPersonInsurance>
            <InsuredPersonCategory></InsuredPersonCategory>
            <InsuredPersonSurname></InsuredPersonSurname>
            <InsuredPersonName></InsuredPersonName>
            <InsuredPersonMiddleName></InsuredPersonMiddleName>
            <InsuredPersonBirthday></InsuredPersonBirthday>
            <InsuredPersonGender></InsuredPersonGender>
            <InsuredPersonBirthplace></InsuredPersonBirthplace>
            <CreatedByCCFullName></CreatedByCCFullName>
            <CreatedByCCLogin></CreatedByCCLogin>
            <CreatedByCCId></CreatedByCCId>
            <UpdatedByCCFullName></UpdatedByCCFullName>
            <UpdateByCCLogin></UpdateByCCLogin>
            <UpdatedByCCId></UpdatedByCCId>
            <AgrId></AgrId>
            <AgrStatus></AgrStatus>
            <DateRegProduct></DateRegProduct>
            <DateCancelInsurance></DateCancelInsurance>
            <ActivityId></ActivityId>
            <DivisionId></DivisionId>
            <PayrollAgreeId></PayrollAgreeId>
            <DirectSalerId></DirectSalerId>
            <VisitPlanDate></VisitPlanDate>
            <VisitPlanTime></VisitPlanTime>
            <OwnerPosId></OwnerPosId>
            <OwnerEmpId></OwnerEmpId>
            <VisitType></VisitType>
            <VisitStartDt></VisitStartDt>
            <VisitEndDt></VisitEndDt>
            <VisitStatus></VisitStatus>
            <VisitComment></VisitComment>
<!--
            <FlagOfDeveloper></FlagOfDeveloper>
            <OptyElectronicRegistration></OptyElectronicRegistration>
            <SubsidyOfDeveloper></SubsidyOfDeveloper>
            <RegionalHousingProgramme></RegionalHousingProgramme>
            <HousingProgrammeName></HousingProgrammeName>
            <MothersPaymentForBank></MothersPaymentForBank>
            <MothersPaymentForDeveloper></MothersPaymentForDeveloper>
            <OptyOnTwoDocuments></OptyOnTwoDocuments>
            <NMSIssueDate></NMSIssueDate>
            <NMSLimitDate></NMSLimitDate>
            <NMSAdditionalSum></NMSAdditionalSum>
            <NMSCurrentSum></NMSCurrentSum>
            <DebtOfRefinancingMortage></DebtOfRefinancingMortage>
            <OtherRefinancingDebt></OtherRefinancingDebt>
            <SumForNeeds></SumForNeeds>
            <RealEstateEncumbrance></RealEstateEncumbrance>
            <CreditPotentialCalcDate></CreditPotentialCalcDate>
-->
            <StartDate></StartDate>
            <ParentOptyNumber></ParentOptyNumber>
            <ComissionPayment></ComissionPayment>
            <PartnerCompany></PartnerCompany>
            <TarifInfo></TarifInfo>
            <Reserved1></Reserved1>
            <Reserved2></Reserved2>
            <Reserved3></Reserved3>
            <Reserved4></Reserved4>
            <Reserved5></Reserved5>
            <Reserved6></Reserved6>
            <Reserved7></Reserved7>
            <Reserved8></Reserved8>
            <Reserved9></Reserved9>
            <Reserved10></Reserved10>
            <Reserved11></Reserved11>
            <Reserved12></Reserved12>
            <Reserved13></Reserved13>
            <Reserved14></Reserved14>
            <Reserved15></Reserved15>
            <EmployeeList>
                <Employee>
                    <Login></Login>
                    <Phone></Phone>
                    <Email></Email>
                </Employee>
            </EmployeeList>
            <MemberList>
                <Member>
                    <LastName></LastName>
                    <FirstName></FirstName>
                    <MiddleName></MiddleName>
                    <BirthDate></BirthDate>
                    <DocNumber></DocNumber>
                    <DocType></DocType>
                    <ClientEPCId></ClientEPCId>
                    <MobilePhone></MobilePhone>
                    <Email></Email>
                    <CustomerValue></CustomerValue>
                    <Status></Status>
                    <Type></Type>
                    <OptyMemberUfsId></OptyMemberUfsId>
                    <PrimaryClient></PrimaryClient>
                    <Income></Income>
                    <IncomeSource></IncomeSource>
                    <ClientCategory></ClientCategory>
                    <AdditionalIncome></AdditionalIncome>
                    <FlagOfAdditionalIncome></FlagOfAdditionalIncome>
                    <Pension></Pension>
                    <FlagOfCurrentLoan></FlagOfCurrentLoan>
                    <ExpenseOnLoan></ExpenseOnLoan>
                    <MarriageStatus></MarriageStatus>
                    <Children></Children>
                    <ChildrenQuantity></ChildrenQuantity>
                    <Dependent></Dependent>
                    <DependentQuantity></DependentQuantity>
                    <AverageExpense></AverageExpense>
                    <Businessman></Businessman>
                    <MarriageAgreement></MarriageAgreement>
                    <Gender></Gender>
                    <ISSpouseRFcitizen></ISSpouseRFcitizen>
                    <TakeIncome></TakeIncome>
                </Member>
            </MemberList>
        </ApplicationInfo>
    </Application>
</IMNotifyApplicationUpdateRq>