<NotifyApplicationUpdateRq>
	<HeaderInfo RqUID="6678855555545sdagsdag324" RqTm="12/05/2016 12:14:00" SPName="urn:sbrfsystems:99-ufs" SystemId="urn:sbrfsystems:99-crm" Method="GetCreditCard"/>
	<Application>
		<ClientInfo>
			<StubId>MH0UQXDE6LWDY0QWRSQZ2ZVMKL1GPAPDOP45N3TIZJB3LAB1MG</StubId>
			<LastName>СЕДОВА</LastName>
			<FirstName>ОКСАНА</FirstName>
			<MiddleName>ВИКТОРОВНА</MiddleName>
			<BirthDate>03/31/1985</BirthDate>
			<PassportSer>6109</PassportSer>
			<PassportNum>573254</PassportNum>
		</ClientInfo>
		<CCApplicationInfo>
			<UFSId>jhjh687UO654</UFSId>
			<IntegrationId/>
			<UKCode>11280101001CU5</UKCode>
			<Channel>4</Channel>
			<Limit>101000</Limit>
			<Currency>RUB</Currency>
			<Rate>12</Rate>
			<Period>12</Period>
			<Comments>Проверка комментария2</Comments>
			<DivisionId>00</DivisionId>
			<CreatedByLogin>USER367</CreatedByLogin>
			<LastAppLogin>USER367</LastAppLogin>
			<Status>6</Status>
			<StatusDetails>Ошибка выпуска карты</StatusDetails>
			<ProductId>521</ProductId>
		</CCApplicationInfo>
	</Application>
</NotifyApplicationUpdateRq>

