<?xml version="1.0" encoding="UTF-8"?>
<EKP01Rs>
	<HeaderInfo ErrorCode="0" ErrorText="" RqUID="00000000000034000000000000000000"/>
	<GetPrivateLoanDetailsRs>
		<OperUID>String</OperUID>
		<SystemId>String</SystemId>
		<LoanRec>
			<ProdId>String</ProdId>
			<IdSpacing>String</IdSpacing>
			<LoanType>String</LoanType>
			<Period>String</Period>
			<CreditingRate>String</CreditingRate>
			<LoanStatus>String</LoanStatus>
			<PrincipalBalance>String</PrincipalBalance>
			<FullRepaymentAmount>String</FullRepaymentAmount>
			<Overdue>Y</Overdue>
			<Accounts>
				<Card>
					<Element>
						<Id>String</Id>
						<Priority>1</Priority>
					</Element>
				</Card>
				<Account>
					<Element>
						<Id>String</Id>
						<Priority>1</Priority>
					</Element>
				</Account>
			</Accounts>
			<BAKS>Y</BAKS>
			<AutoGrantion>N</AutoGrantion>
			<ApplicationNumberCA>String</ApplicationNumberCA>
			<CustRec>
				<CustInfo>
					<PersonInfo>
						<PersonRole>Y</PersonRole>
						<PersonName>
							<LastName>String</LastName>
							<FirstName>String</FirstName>
							<MiddleName>String</MiddleName>
							<CompanyName>String</CompanyName>
						</PersonName>
					</PersonInfo>
				</CustInfo>
			</CustRec>
			<AgencyAddress>String</AgencyAddress>
			<EarlyRepayment>
				<Amount>String</Amount>
				<Date>2015-11-03</Date>
				<Status>Исполнено</Status>
				<Account>String</Account>
				<RepaymentChannel>String</RepaymentChannel>
				<TerminationRequestId>String</TerminationRequestId>
				<ERIBRequestID>String</ERIBRequestID>
			</EarlyRepayment>
			<AcctBalOnDate>
				<BalType>BAKS_EXT_OVE</BalType>
				<BalName>String</BalName>
				<CurAmt>String</CurAmt>
				<NextAmt>34545</NextAmt>
				<AcctCur>34455</AcctCur>
				<DebtAccount>String</DebtAccount>
				<Priority>String</Priority>
				<AcctCount>String</AcctCount>
				<EffDt>2015-11-03</EffDt>
			</AcctBalOnDate>
			<CreditSum>String</CreditSum>
		</LoanRec>
	</GetPrivateLoanDetailsRs>
</EKP01Rs>
